cmov/__init__.py
cmov/components/SF-Pro-Text-Medium.otf
cmov/components/__init__.py
cmov/components/align.py
cmov/components/box.py
cmov/components/text.py
cmov/core/__init__.py
cmov/core/animation.py
cmov/core/component.py
cmov/core/composite_anim.py
cmov/core/scene.py
cmov/easing/__init__.py
cmov/easing/curves.py
cmov/utils/__init__.py
cmov/utils/color.py
cmov/utils/time.py
cmov-0.1.9.dist-info/METADATA
cmov-0.1.9.dist-info/WHEEL
cmov-0.1.9.dist-info/licenses/LICENSE
cmov-0.1.9.dist-info/RECORD
