Metadata-Version: 2.4
Name: cmov
Version: 0.1.9
Summary: A high-level Python library for programmatic timeline-based video animation and dynamic scene creation.
License: MIT
License-File: LICENSE
Author: Dylan DiBeneditto
Author-email: dibenedittod@gmail.com
Requires-Python: >=3.12
Classifier: License :: OSI Approved :: MIT License
Classifier: Programming Language :: Python :: 3
Classifier: Programming Language :: Python :: 3.12
Classifier: Programming Language :: Python :: 3.13
Classifier: Programming Language :: Python :: 3.14
Requires-Dist: fmov
Requires-Dist: pillow
